odoo/addons/stock_vertical_lift_packaging_type/README.rst
odoo/addons/stock_vertical_lift_packaging_type/__init__.py
odoo/addons/stock_vertical_lift_packaging_type/__manifest__.py
odoo/addons/stock_vertical_lift_packaging_type/i18n/it.po
odoo/addons/stock_vertical_lift_packaging_type/i18n/stock_vertical_lift_packaging_type.pot
odoo/addons/stock_vertical_lift_packaging_type/readme/CONTRIBUTORS.rst
odoo/addons/stock_vertical_lift_packaging_type/readme/CREDITS.rst
odoo/addons/stock_vertical_lift_packaging_type/readme/DESCRIPTION.rst
odoo/addons/stock_vertical_lift_packaging_type/static/description/icon.png
odoo/addons/stock_vertical_lift_packaging_type/static/description/index.html
odoo/addons/stock_vertical_lift_packaging_type/views/shuttle_screen_templates.xml
odoo14_addon_stock_vertical_lift_packaging_type-14.0.1.0.1.dev3.dist-info/METADATA
odoo14_addon_stock_vertical_lift_packaging_type-14.0.1.0.1.dev3.dist-info/WHEEL
odoo14_addon_stock_vertical_lift_packaging_type-14.0.1.0.1.dev3.dist-info/top_level.txt
odoo14_addon_stock_vertical_lift_packaging_type-14.0.1.0.1.dev3.dist-info/RECORD
